{
   "format_version" : "1.14.0",
   "sound_definitions" : {
      "mob.skeleton.shoot" : {
         "__use_legacy_max_distance" : "true",
         "sounds" : [ "sounds/random/bow" ]
      },
      "mob.wither_skeleton.death" : {
         "__use_legacy_max_distance" : "true",
         "category" : "hostile",
         "sounds" : [
			"sounds/mob/wither_skeleton/death1",
			"sounds/mob/wither_skeleton/death2"
		]
      },
      "mob.wither_skeleton.hurt" : {
         "__use_legacy_max_distance" : "true",
         "category" : "hostile",
         "sounds" : [
            "sounds/mob/wither_skeleton/hurt1",
            "sounds/mob/wither_skeleton/hurt2",
            "sounds/mob/wither_skeleton/hurt3",
            "sounds/mob/wither_skeleton/hurt4"
         ]
      },
      "mob.wither_skeleton.say" : {
         "__use_legacy_max_distance" : "true",
         "category" : "hostile",
         "sounds" : [
            "sounds/mob/wither_skeleton/idle1",
            "sounds/mob/wither_skeleton/idle2",
            {
               "load_on_low_memory" : true,
               "name" : "sounds/mob/wither_skeleton/idle3"
            }
         ]
      },
      "mob.wither_skeleton.step" : {
         "__use_legacy_max_distance" : "true",
         "category" : "hostile",
         "sounds" : [
            {
               "load_on_low_memory" : true,
               "name" : "sounds/mob/wither_skeleton/step1"
            },
            "sounds/mob/wither_skeleton/step2",
            "sounds/mob/wither_skeleton/step3",
            "sounds/mob/wither_skeleton/step4"
         ]
      }
   }
}
